README.md
setup.py
topmine/__init__.py
topmine/dirichlet.py
topmine/phrase_lda.py
topmine/phrase_mining.py
topmine/run_phrase_lda.py
topmine/run_phrase_mining.py
topmine/stopwords.py
topmine/utils.py
topmine.egg-info/PKG-INFO
topmine.egg-info/SOURCES.txt
topmine.egg-info/dependency_links.txt
topmine.egg-info/requires.txt
topmine.egg-info/top_level.txt