Metadata-Version: 1.1
Name: topmine
Version: 0.1.1
Summary: topic mining
Home-page: https://github.com/WangHexie/topmine
Author: UNKNOWN
Author-email: test@test.com
License: BSD 2-clause
Platform: UNKNOWN
Classifier: Development Status :: 1 - Planning
Classifier: Intended Audience :: Science/Research
Classifier: License :: OSI Approved :: BSD License
